odoo/addons/account_statement_import_online/README.rst
odoo/addons/account_statement_import_online/__init__.py
odoo/addons/account_statement_import_online/__manifest__.py
odoo/addons/account_statement_import_online/data/account_statement_import_online.xml
odoo/addons/account_statement_import_online/i18n/account_statement_import_online.pot
odoo/addons/account_statement_import_online/i18n/ca.po
odoo/addons/account_statement_import_online/i18n/ca_ES.po
odoo/addons/account_statement_import_online/i18n/de.po
odoo/addons/account_statement_import_online/i18n/es.po
odoo/addons/account_statement_import_online/i18n/it.po
odoo/addons/account_statement_import_online/i18n/lv.po
odoo/addons/account_statement_import_online/i18n/nl.po
odoo/addons/account_statement_import_online/i18n/tr.po
odoo/addons/account_statement_import_online/models/__init__.py
odoo/addons/account_statement_import_online/models/account_journal.py
odoo/addons/account_statement_import_online/models/online_bank_statement_provider.py
odoo/addons/account_statement_import_online/readme/CONFIGURE.md
odoo/addons/account_statement_import_online/readme/CONTRIBUTORS.md
odoo/addons/account_statement_import_online/readme/DESCRIPTION.md
odoo/addons/account_statement_import_online/readme/USAGE.md
odoo/addons/account_statement_import_online/security/ir.model.access.csv
odoo/addons/account_statement_import_online/security/online_bank_statement_provider.xml
odoo/addons/account_statement_import_online/static/description/icon.png
odoo/addons/account_statement_import_online/static/description/index.html
odoo/addons/account_statement_import_online/tests/__init__.py
odoo/addons/account_statement_import_online/tests/online_bank_statement_provider_dummy.py
odoo/addons/account_statement_import_online/tests/test_account_bank_statement_import_online.py
odoo/addons/account_statement_import_online/views/account_journal.xml
odoo/addons/account_statement_import_online/views/actions.xml
odoo_addon_account_statement_import_online-18.0.1.1.2.5.dist-info/METADATA
odoo_addon_account_statement_import_online-18.0.1.1.2.5.dist-info/WHEEL
odoo_addon_account_statement_import_online-18.0.1.1.2.5.dist-info/top_level.txt
odoo_addon_account_statement_import_online-18.0.1.1.2.5.dist-info/RECORD
