Metadata-Version: 2.1
Name: odoo-addon-account_statement_import_online
Version: 18.0.1.1.2.5
Requires-Python: >=3.10
Requires-Dist: odoo-addon-account_statement_import_base==18.0.*
Requires-Dist: odoo==18.0.*
Summary: Online bank statements update
Home-page: https://github.com/OCA/bank-statement-import
License: AGPL-3
Author: CorporateHub, Odoo Community Association (OCA)
Author-email: support@odoo-community.org
Classifier: Programming Language :: Python
Classifier: Framework :: Odoo
Classifier: Framework :: Odoo :: 18.0
Classifier: License :: OSI Approved :: GNU Affero General Public License v3
